trytond/modules/akademy_matriculation_confirmation/LICENSE
trytond/modules/akademy_matriculation_confirmation/README.md
trytond/modules/akademy_matriculation_confirmation/__init__.py
trytond/modules/akademy_matriculation_confirmation/matriculation.py
trytond/modules/akademy_matriculation_confirmation/matriculation.xml
trytond/modules/akademy_matriculation_confirmation/tryton.cfg
trytond/modules/akademy_matriculation_confirmation/locale/en.po
trytond/modules/akademy_matriculation_confirmation/locale/fr.po
trytond/modules/akademy_matriculation_confirmation/locale/pt.po
trytond/modules/akademy_matriculation_confirmation/security/access_rights_admin.xml
trytond/modules/akademy_matriculation_confirmation/security/access_rights_direct.xml
trytond/modules/akademy_matriculation_confirmation/security/access_rights_secret.xml
trytond/modules/akademy_matriculation_confirmation/security/access_rights_student.xml
trytond/modules/akademy_matriculation_confirmation/security/access_rights_teacher.xml
trytond/modules/akademy_matriculation_confirmation/tests/__init__.py
trytond/modules/akademy_matriculation_confirmation/tests/test_matriculation.py
trytond/modules/akademy_matriculation_confirmation/view/changematriculation_wizcreate_form.xml
trytond/modules/akademy_matriculation_confirmation/view/matriculation_wizcreate_form.xml
akademy_matriculation_confirmation-1.1.0.dist-info/METADATA
akademy_matriculation_confirmation-1.1.0.dist-info/WHEEL
akademy_matriculation_confirmation-1.1.0.dist-info/licenses/LICENSE
akademy_matriculation_confirmation-1.1.0.dist-info/RECORD
