Metadata-Version: 2.4
Name: akademy_matriculation_confirmation
Version: 1.1.0
Summary: SAGE Education is a free and open-source project for educators, educational institutions, and governments.
Project-URL: Homepage, https://comunidadedosaber.ao
Project-URL: Documentation, https://docs.comunidadedosaber.ao
Project-URL: Demo, https://sage.comunidadedosaber.ao
Project-URL: Repository, https://github.com/zacariasjuliano/akademy-matriculation_confirmation
Project-URL: Bug Tracker, https://github.com/zacariasjuliano/akademy-matriculation_confirmation/issues
Project-URL: Changelog, https://github.com/zacariasjuliano/akademy-matriculation_confirmation/blob/main/CHANGELOG.md
Author-email: Zacarias Juliano Capingala <zacariasjuliano@gmail.com>
License: GPL-3.0-or-later
License-File: LICENSE
Keywords: SGA,SGE,SIE,education,sage-edu,school
Requires-Python: >=3.8
Requires-Dist: akademy-classe~=1.1
Requires-Dist: akademy-matriculation~=1.1
